README.rst
setup.py
warp.py
warp_proxy.egg-info/PKG-INFO
warp_proxy.egg-info/SOURCES.txt
warp_proxy.egg-info/dependency_links.txt
warp_proxy.egg-info/entry_points.txt
warp_proxy.egg-info/top_level.txt