Metadata-Version: 1.1
Name: warp-proxy
Version: 0.1.0
Summary: Simple http transparent proxy made in Python 3.4
Home-page: https://github.com/devunt/warp
Author: JuneHyeon Bae
Author-email: devunt@gmail.com
License: MIT License
Platform: UNKNOWN
Classifier: Development Status :: 3 - Alpha
Classifier: Environment :: Console
Classifier: Environment :: Web Environment
Classifier: Intended Audience :: End Users/Desktop
Classifier: License :: OSI Approved :: MIT License
Classifier: Operating System :: POSIX
Classifier: Programming Language :: Python :: 3
Classifier: Programming Language :: Python :: 3.4
Classifier: Programming Language :: Python :: Implementation :: CPython
Classifier: Topic :: Internet :: Proxy Servers
Classifier: Topic :: Internet :: WWW/HTTP
